{
    "header": {
        "order_number": "91818163653277073250",
        "customer": "x",
        "invoice_number": "INV-322172",
        "date": "2025-03-24",
        "price": {
            "total_sum": 60.0,
            "currency": "K\u010d"
        }
    },
    "detail": {
        "category": "Gaming",
        "product_name": "x",
        "price_amount": 10.0,
        "additional_service": {
            "service": "N",
            "service_type": "None",
            "service_price": 0.0
        }
    },
    "transportation": {
        "transporter": "DHL",
        "country": "Czech Republic",
        "size": "small",
        "transport_price": 50.0
    }
}